[
  {
    "ApiId": "/providers/microsoft.powerapps/apis/shared_sharepointonline",
    "CdpRevision": {
      "BaseUrl": "/",
      "LastChangedTimeString": "2024-02-12T21:23:17.3090000Z",
      "RevisionNumber": 1
    },
    "ConnectedDataSourceInfoNameMapping": {
      "{Attachments}": "Attachments",
      "{Attachments}@odata.type": "{Attachments} ({Attachments}@odata.type)",
      "{FilenameWithExtension}": "File name with extension",
      "{FullPath}": "Full Path",
      "{HasAttachments}": "Has attachments",
      "{Identifier}": "Identifier",
      "{IsFolder}": "IsFolder",
      "{Link}": "Link to item",
      "{ModerationComment}": "Comments associated with the content approval of this list item",
      "{ModerationStatus}": "Content approval status",
      "{Name}": "Name",
      "{Path}": "Folder path",
      "{Thumbnail}": "Thumbnail",
      "{TriggerWindowEndToken}": "Trigger Window End Token",
      "{TriggerWindowStartToken}": "Trigger Window Start Token",
      "{VersionNumber}": "Version number",
      "Active": "Active",
      "AllocatedAssets": "Allocated Assets",
      "AllocatedAssets#Id": "Allocated Assets Id",
      "AllocatedAssets@odata.type": "AllocatedAssets (AllocatedAssets@odata.type)",
      "Author": "Created By",
      "Author#Claims": "Created By Claims",
      "Company": "Company",
      "ComplianceAssetId": "Compliance Asset Id",
      "CostCentre": "Cost Centre",
      "CostCentre#Id": "Cost Centre Id",
      "Created": "Created",
      "DEEmployee": "GC Employee Non Microsoft",
      "Department": "Department",
      "Department#Id": "Department Id",
      "Editor": "Modified By",
      "Editor#Claims": "Modified By Claims",
      "Email": "Contact Email",
      "GCEmployee": "GC Employee - Microsoft",
      "GCEmployee#Claims": "GC Employee - Microsoft Claims",
      "ID": "ID",
      "Modified": "Modified",
      "OData__ColorTag": "Color Tag",
      "PhoneNumber": "Phone Number",
      "PhoneNumber#Id": "Phone Number Id",
      "TeamNo": "Team No.",
      "Title": "Title"
    },
    "DatasetName": "https://gcontrol365.sharepoint.com/sites/ITAssetManagement",
    "EncodeDataset": true,
    "IsSampleData": false,
    "IsWritable": true,
    "Name": "Asset Management List",
    "Type": "ConnectedDataSourceInfo"
  }
]